README.md
setup.py
key_store/__init__.py
key_store/helpers.py
key_store/key_store.py
key_store.egg-info/PKG-INFO
key_store.egg-info/SOURCES.txt
key_store.egg-info/dependency_links.txt
key_store.egg-info/top_level.txt