Metadata-Version: 1.2
Name: key-store
Version: 0.1.0
Summary: Helper functions for getting objects easily from a list with multiple filter keys
Home-page: https://github.com/rimaddo/key-store
Maintainer: Rachel
Maintainer-email: rachel.isabella.madden@gmail.com
License: MIT
Platform: UNKNOWN
Requires-Python: >3.7.0
